googlelens/__init__.py
googlelens/googlelens.py
GoogleLens-0.1.0.dist-info/LICENSE
GoogleLens-0.1.0.dist-info/METADATA
GoogleLens-0.1.0.dist-info/WHEEL
GoogleLens-0.1.0.dist-info/top_level.txt
GoogleLens-0.1.0.dist-info/RECORD
