Metadata-Version: 2.1
Name: GoogleLens
Version: 0.1.0
Summary: A library for interacting with the Aparat API
Home-page: https://github.com/AbolDev/GoogleLens
Author: Abol
Author-email: abaqry8686@gmail.com
License: MIT
Project-URL: Bug Tracker, https://github.com/AbolDev/GoogleLens/issues
Project-URL: Source Code, https://github.com/AbolDev/GoogleLens
Keywords: python,library,Google,Google-api,GoogleLens-api,GoogleLens-lib,Google-lib,GoogleLens-python,Google-python
Classifier: Programming Language :: Python :: 3
Classifier: License :: OSI Approved :: MIT License
Classifier: Operating System :: OS Independent
Classifier: Development Status :: 4 - Beta
Classifier: Intended Audience :: Developers
Classifier: Topic :: Software Development :: Libraries :: Python Modules
Requires-Python: >=3.6
License-File: LICENSE
Requires-Dist: requests
Requires-Dist: beautifulsoup4
